frozen_cub/__init__.py
frozen_cub/__main__.py
frozen_cub/api.py
frozen_cub/common.cp312-win_amd64.pyd
frozen_cub/common.cp313-win_amd64.pyd
frozen_cub/common.pxd
frozen_cub/common.pyx
frozen_cub/dispatcher.py
frozen_cub/frozen.cp312-win_amd64.pyd
frozen_cub/frozen.cp313-win_amd64.pyd
frozen_cub/frozen.pxd
frozen_cub/frozen.pyi
frozen_cub/frozen.pyx
frozen_cub/lru_cache.cp312-win_amd64.pyd
frozen_cub/lru_cache.cp313-win_amd64.pyd
frozen_cub/lru_cache.pxd
frozen_cub/lru_cache.pyi
frozen_cub/lru_cache.pyx
frozen_cub/py.typed
frozen_cub/utils.cp312-win_amd64.pyd
frozen_cub/utils.cp313-win_amd64.pyd
frozen_cub/utils.pxd
frozen_cub/utils.pyi
frozen_cub/utils.pyx
frozen_cub/_internal/__init__.py
frozen_cub/_internal/_cmds.py
frozen_cub/_internal/_exit_code.py
frozen_cub/_internal/_info.py
frozen_cub/_internal/_version.pyi
frozen_cub/_internal/_versioning.py
frozen_cub/_internal/cli.py
frozen_cub/_internal/debug.py
frozen_cub-0.1.9.dist-info/METADATA
frozen_cub-0.1.9.dist-info/WHEEL
frozen_cub-0.1.9.dist-info/entry_points.txt
frozen_cub-0.1.9.dist-info/RECORD
