Metadata-Version: 2.4
Name: frozen-cub
Version: 0.1.9
Summary: A set of C and Python implementations of immutable, hashable, and performant frozen objects.
Author-email: chaz <bright.lid5647@fastmail.com>
Requires-Python: >=3.12
